drf_manipulation/__init__.py
drf_manipulation/models.py
drf_manipulation/serializers.py
drf_manipulation-0.1.3.dist-info/LICENSE
drf_manipulation-0.1.3.dist-info/WHEEL
drf_manipulation-0.1.3.dist-info/METADATA
drf_manipulation-0.1.3.dist-info/RECORD
