Metadata-Version: 2.1
Name: drf-manipulation
Version: 0.1.3
Summary: Tools to quickly add manipulation log fields to your Django project
Author: Xurvan
Classifier: License :: OSI Approved :: Apache Software License
Project-URL: Source, https://github.com/xanigo/drf-manipulation
